windows_terminal_setup/__init__.py
windows_terminal_setup/change_terminal_settings.py
windows_terminal_setup/fancy_prompt_themes.py
croshell-0.0.1.dist-info/METADATA
croshell-0.0.1.dist-info/WHEEL
croshell-0.0.1.dist-info/top_level.txt
croshell-0.0.1.dist-info/RECORD
